prometheus_flask_instrumentator/__init__.py
prometheus_flask_instrumentator/flask_instrumentation.py
prometheus_flask_instrumentator-20.7.5.dist-info/LICENSE.txt
prometheus_flask_instrumentator-20.7.5.dist-info/WHEEL
prometheus_flask_instrumentator-20.7.5.dist-info/METADATA
prometheus_flask_instrumentator-20.7.5.dist-info/RECORD
