Metadata-Version: 2.1
Name: prometheus-flask-instrumentator
Version: 20.7.5
Summary: Instruments Flask API transparently
Home-page: https://github.com/trallnag/prometheus-flask-instrumentator
License: MIT
Keywords: prometheus,instrumentation,flask,monitoring,metrics
Author: Tim Schwenke
Author-email: tim.schwenke+trallnag@protonmail.ch
Requires-Python: >=3.6,<4.0
Classifier: Development Status :: 4 - Beta
Classifier: Intended Audience :: Developers
Classifier: License :: OSI Approved :: MIT License
Classifier: Programming Language :: Python :: 3
Classifier: Programming Language :: Python :: 3.6
Classifier: Programming Language :: Python :: 3.7
Classifier: Programming Language :: Python :: 3.8
Classifier: Topic :: System :: Logging
Classifier: Topic :: System :: Monitoring
Requires-Dist: flask (>=1,<2)
Requires-Dist: prometheus-client (>=0.8,<0.9)
Project-URL: Repository, https://github.com/trallnag/prometheus-flask-instrumentator
